cantoseg/__init__.py
cantoseg/cantoseg.py
cantoseg/merged_dict.txt
cantoseg/version.py
cantoseg-0.0.1.dist-info/LICENSE
cantoseg-0.0.1.dist-info/METADATA
cantoseg-0.0.1.dist-info/WHEEL
cantoseg-0.0.1.dist-info/top_level.txt
cantoseg-0.0.1.dist-info/RECORD
